MinimumValue/MinimumValue.py
MinimumValue/__init__.py
MinimumValue-0.1.0.dist-info/METADATA
MinimumValue-0.1.0.dist-info/WHEEL
MinimumValue-0.1.0.dist-info/top_level.txt
MinimumValue-0.1.0.dist-info/RECORD
